pydatatest/__init__.py
pydatatest/api/__init__.py
pydatatest/common/__init__.py
pydatatest/common/http.py
pydatatest/common/inject.py
pydatatest/common/runner.py
pydatatest/common/testcase.py
pydatatest/data/__init__.py
pydatatest/data/csv.py
pydatatest/data/yaml.py
pydatatest/util/__init__.py
pydatatest/util/csv.py
pydatatest/util/inspect.py
pydatatest/util/yaml.py
pydatatest-1.0.6.dist-info/LICENSE
pydatatest-1.0.6.dist-info/METADATA
pydatatest-1.0.6.dist-info/WHEEL
pydatatest-1.0.6.dist-info/RECORD
