Metadata-Version: 2.3
Name: pydatatest
Version: 1.0.6
Summary: Data driven python test framework
License: MIT
Keywords: test,data driven,test framework
Author: aak1247
Author-email: aak1247@126.com
Requires-Python: >=3.9,<4.0
Classifier: License :: OSI Approved :: MIT License
Classifier: Programming Language :: Python :: 3
Classifier: Programming Language :: Python :: 3.9
Classifier: Programming Language :: Python :: 3.10
Classifier: Programming Language :: Python :: 3.11
Classifier: Programming Language :: Python :: 3.12
Classifier: Programming Language :: Python :: 3.13
Requires-Dist: pyyaml (>=5.1,<6.0)
Requires-Dist: requests (>=2.28.1,<3.0.0)
Project-URL: Homepage, https://github.com/aak1247/PyDataTest
Project-URL: Repository, https://github.com/aak1247/PyDataTest
